stegapy/__init__.py
stegapy/stegabmp.py
stegapy/stegatxt.py
stegapy/stegawav.py
stegapy-0.0.1.dist-info/LICENSE
stegapy-0.0.1.dist-info/METADATA
stegapy-0.0.1.dist-info/WHEEL
stegapy-0.0.1.dist-info/top_level.txt
stegapy-0.0.1.dist-info/RECORD
