Metadata-Version: 2.1
Name: stegapy
Version: 0.0.1
Summary: A steganography simple Python project
Home-page: UNKNOWN
Author: Ivan Foke
Author-email: ivan.foke@gmail.com
License: UNKNOWN
Platform: UNKNOWN
Classifier: Programming Language :: Python :: 3
Classifier: License :: OSI Approved :: MIT License
Classifier: Operating System :: OS Independent
Requires-Python: >=3.6
